{"is_source_file": true, "format": "JavaScript", "description": "This file provides utility functions to interact with a scores API in a Tic-Tac-Toe platform. It includes functions to fetch and save scores via HTTP requests.", "external_files": ["fetch"], "external_methods": ["fetch"], "published": ["fetchScores", "saveScore"], "classes": [], "methods": [{"name": "fetchScores(mode)", "description": "Fetches scores from the API for a specified game mode ('single' or 'two'). Returns score object or null on failure.", "scope": "", "scopeKind": ""}, {"name": "saveScore(mode, scores)", "description": "Saves scores to the API for a specified game mode. Attempts POST request; silently fails on error.", "scope": "", "scopeKind": ""}], "calls": ["fetch", "fetch", "fetch"], "search-terms": ["scoreApi", "fetchScores", "saveScore", "API_BASE"], "state": 2, "file_id": 16, "knowledge_revision": 35, "git_revision": "", "ctags": [{"_type": "tag", "name": "API_BASE", "path": "/home/kavia/workspace/code-generation/online-tic-tac-toe-platform-43328-43347/tic_tac_frontend/src/utils/scoreApi.js", "pattern": "/^const API_BASE = \"\\/api\\/scores\"; \\/\\/ Adjust if the actual endpoint differs$/", "language": "JavaScript", "kind": "constant"}, {"_type": "tag", "name": "fetchScores", "path": "/home/kavia/workspace/code-generation/online-tic-tac-toe-platform-43328-43347/tic_tac_frontend/src/utils/scoreApi.js", "pattern": "/^export async function fetchScores(mode) {$/", "language": "JavaScript", "kind": "function", "signature": "(mode)"}, {"_type": "tag", "name": "saveScore", "path": "/home/kavia/workspace/code-generation/online-tic-tac-toe-platform-43328-43347/tic_tac_frontend/src/utils/scoreApi.js", "pattern": "/^export async function saveScore(mode, scores) {$/", "language": "JavaScript", "kind": "function", "signature": "(mode, scores)"}], "hash": "f5ad6e87d9169780f0c0d0ca2e6f439b", "format-version": 4, "code-base-name": "tic_tac_frontend", "filename": "tic_tac_frontend/src/utils/scoreApi.js", "revision_history": [{"35": ""}]}